Metadata-Version: 2.1
Name: fidjax
Version: 1.0.1
Summary: Frechet Inception Distance in JAX.
Home-page: http://github.com/danijar/fidjax
Classifier: Intended Audience :: Science/Research
Classifier: License :: OSI Approved :: MIT License
Classifier: Programming Language :: Python :: 3
